CHANGES.txt
README.txt
setup.py
src/cloudooo/__init__.py
src/cloudooo.handler.pdf.egg-info/PKG-INFO
src/cloudooo.handler.pdf.egg-info/SOURCES.txt
src/cloudooo.handler.pdf.egg-info/dependency_links.txt
src/cloudooo.handler.pdf.egg-info/entry_points.txt
src/cloudooo.handler.pdf.egg-info/namespace_packages.txt
src/cloudooo.handler.pdf.egg-info/requires.txt
src/cloudooo.handler.pdf.egg-info/top_level.txt
src/cloudooo/handler/__init__.py
src/cloudooo/handler/pdf/__init__.py
src/cloudooo/handler/pdf/handler.py
src/cloudooo/handler/pdf/tests/__init__.py
src/cloudooo/handler/pdf/tests/runPDFHandlerUnitTest.py
src/cloudooo/handler/pdf/tests/testPDFHandler.py
src/cloudooo/handler/pdf/tests/testServer.py
src/cloudooo/handler/pdf/tests/data/test.pdf