Metadata-Version: 1.0
Name: cloudooo.handler.pdf
Version: 0.1
Summary: Python Package to handler PDF documents
Home-page: UNKNOWN
Author: Gabriel M. Monnerat
Author-email: gabriel@tiolive.com
License: GPL
Keywords: python xpdf
Platform: UNKNOWN
Classifier: Programming Language :: Python :: 2.6
Classifier: Natural Language :: English
